gluster_stats/__init__.py
gluster_stats/gluster_stats.py
gluster_stats-1.2.2.dist-info/DESCRIPTION.rst
gluster_stats-1.2.2.dist-info/METADATA
gluster_stats-1.2.2.dist-info/RECORD
gluster_stats-1.2.2.dist-info/WHEEL
gluster_stats-1.2.2.dist-info/entry_points.txt
gluster_stats-1.2.2.dist-info/metadata.json
gluster_stats-1.2.2.dist-info/top_level.txt
