Metadata-Version: 2.0
Name: gluster-stats
Version: 1.2.2
Summary: Display gluster stats
Home-page: https://github.com/danrue/gluster_stats
Author: Dan Rue
Author-email: drue@therub.org
License: BSD
Keywords: gluster monitoring
Platform: UNKNOWN
Classifier: Development Status :: 3 - Alpha
Classifier: Intended Audience :: Developers
Classifier: License :: OSI Approved :: BSD License
Classifier: Natural Language :: English
Classifier: Programming Language :: Python :: 2
Classifier: Programming Language :: Python :: 2.6
Classifier: Programming Language :: Python :: 2.7
Classifier: Programming Language :: Python :: 3
Classifier: Programming Language :: Python :: 3.3
Classifier: Programming Language :: Python :: 3.4
Classifier: Programming Language :: Python :: 3.5
Requires-Dist: future
